_pulsar.cpython-313-x86_64-linux-gnu.so
pulsar/__about__.py
pulsar/__init__.py
pulsar/asyncio.py
pulsar/exceptions.py
pulsar/tableview.py
pulsar/functions/__init__.py
pulsar/functions/context.py
pulsar/functions/function.py
pulsar/functions/serde.py
pulsar/schema/__init__.py
pulsar/schema/definition.py
pulsar/schema/schema.py
pulsar/schema/schema_avro.py
pulsar_client.libs/libpulsar-1a476c2c.so
pulsar_client-3.9.0.dist-info/METADATA
pulsar_client-3.9.0.dist-info/WHEEL
pulsar_client-3.9.0.dist-info/top_level.txt
pulsar_client-3.9.0.dist-info/RECORD
pulsar_client-3.9.0.dist-info/licenses/LICENSE
pulsar_client-3.9.0.dist-info/licenses/NOTICE
